cosmicpi/__init__.py
cosmicpi/config.py
cosmicpi/rest/__init__.py
cosmicpi/rest/app.py
cosmicpi/rest/auth.py
cosmicpi/rest/histogram.py
cosmicpi/rest/series.py
cosmicpi/rest/wifi.py
cosmicpi/storage/__init__.py
cosmicpi/storage/cosmicpi.sqlite3
cosmicpi/ui/__init__.py
cosmicpi/ui/index.html
cosmicpi/ui/dist/674f50d287a8c48dc19ba404d20fe713.eot
cosmicpi/ui/dist/912ec66d7572ff821749319396470bde.svg
cosmicpi/ui/dist/af7ae505a9eed503f8b8e6982036873e.woff2
cosmicpi/ui/dist/b06871f281fee6b241d60582ae9369b9.ttf
cosmicpi/ui/dist/background_mountains.jpg
cosmicpi/ui/dist/build.js
cosmicpi/ui/dist/build.js.map
cosmicpi/ui/dist/fee66e712a8a08eef5805a46892932ad.woff
cosmicpi/ui/dist/fontawesome-webfont.svg
cosmicpi/ui/dist/loader.gif
cosmicpi/ui/dist/logo.png
cosmicpi-1.5.8.data/scripts/cosmicpi-dbcleaner
cosmicpi-1.5.8.data/scripts/cosmicpi-detector
cosmicpi-1.5.8.data/scripts/cosmicpi-mqtt
cosmicpi-1.5.8.data/scripts/cosmicpi-rest
cosmicpi-1.5.8.data/scripts/cosmicpi-ui
etc/cosmicpi.config
etc/systemd/system/cosmicpi-dbcleaner.service
etc/systemd/system/cosmicpi-detector.service
etc/systemd/system/cosmicpi-mqtt.service
etc/systemd/system/cosmicpi-ui.service
cosmicpi-1.5.8.dist-info/LICENSE
cosmicpi-1.5.8.dist-info/METADATA
cosmicpi-1.5.8.dist-info/WHEEL
cosmicpi-1.5.8.dist-info/top_level.txt
cosmicpi-1.5.8.dist-info/RECORD
