Metadata-Version: 2.1
Name: cosmicpi
Version: 1.5.8
Summary: UI for the CosmicPi cosmic ray detector
Home-page: http://cosmicpi.org/
Maintainer: Cosmic Pi Team
Maintainer-email: info@cosmicpi.org
License: GPL V2
Project-URL: Bug Tracker, https://github.com/CosmicPi/cosmicpi-rpi_V1.5/issues
Project-URL: Documentation, https://github.com/CosmicPi/cosmicpi-rpi_V1.5/blob/master/README.md
Project-URL: Source Code, https://github.com/CosmicPi/cosmicpi-rpi_V1.5
Platform: noarch
Requires-Dist: configparser
Requires-Dist: flask
Requires-Dist: flask-cors
Requires-Dist: flask-restful
Requires-Dist: matplotlib
Requires-Dist: numpy
Requires-Dist: pyserial
